schemaless/__init__.py
schemaless/bases.py
schemaless/commit.py
schemaless/config.py
schemaless/configator.py
schemaless/delta.py
schemaless/domain.py
schemaless/http_client.py
schemaless/rid.py
schemaless/utils.py
schemaless/version_control.py
schemaless/webhook.py
schemaless/webhook_policy.py
schemaless-0.0.11.dist-info/METADATA
schemaless-0.0.11.dist-info/WHEEL
schemaless-0.0.11.dist-info/RECORD
