Metadata-Version: 2.1
Name: schemaless
Version: 0.0.11
Summary: 
Author: Amin Jamal
Author-email: a.jamal@greyrook.com
Requires-Python: >=3.9,<4.0
Classifier: Programming Language :: Python :: 3
Classifier: Programming Language :: Python :: 3.9
Classifier: Programming Language :: Python :: 3.10
Classifier: Programming Language :: Python :: 3.11
Classifier: Programming Language :: Python :: 3.12
Requires-Dist: cloudevents (>=1.10.1,<2.0.0)
Requires-Dist: httpx (>=0.25.1,<0.26.0)
Requires-Dist: pydantic (>=2.5.1,<3.0.0)
Requires-Dist: pydantic-settings (>=2.1.0,<3.0.0)
